db0mb3r/__init__.py
db0mb3r/cli.py
db0mb3r/main.py
db0mb3r/service.py
db0mb3r/utils.py
db0mb3r/app/__init__.py
db0mb3r/app/main.py
db0mb3r/app/models.py
db0mb3r/app/status.py
db0mb3r/app/routers/__init__.py
db0mb3r/app/routers/attack.py
db0mb3r/app/routers/index.py
db0mb3r/app/routers/services.py
db0mb3r/app/static/css/bootstrap.min.css
db0mb3r/app/static/css/bootstrap.min.css.map
db0mb3r/app/static/css/index.css
db0mb3r/app/static/css/intlTelInput.min.css
db0mb3r/app/static/img/flags.png
db0mb3r/app/static/img/flags@2x.png
db0mb3r/app/static/js/index.js
db0mb3r/app/static/js/intlTelInput.min.js
db0mb3r/app/static/js/progressbar.min.js
db0mb3r/app/static/js/progressbar.min.js.map
db0mb3r/app/templates/index.html
db0mb3r/services/3040.py
db0mb3r/services/585gold.py
db0mb3r/services/585zolotoy.py
db0mb3r/services/aisttaxi.py
db0mb3r/services/alfalife.py
db0mb3r/services/allo.py
db0mb3r/services/alltime.py
db0mb3r/services/alpari.py
db0mb3r/services/apteka.py
db0mb3r/services/atprime.py
db0mb3r/services/avtoobzvon.py
db0mb3r/services/bamperby.py
db0mb3r/services/bartokyo.py
db0mb3r/services/beltelecom.py
db0mb3r/services/benzuber.py
db0mb3r/services/bluefin.py
db0mb3r/services/boosty.py
db0mb3r/services/burgerking.py
db0mb3r/services/buzzols.py
db0mb3r/services/call2friends.py
db0mb3r/services/callmyphone.py
db0mb3r/services/carsmile.py
db0mb3r/services/cashu.py
db0mb3r/services/chefmarket.py
db0mb3r/services/cian.py
db0mb3r/services/cinema5.py
db0mb3r/services/citilink.py
db0mb3r/services/city24.py
db0mb3r/services/cleversite.py
db0mb3r/services/comfy.py
db0mb3r/services/creditter.py
db0mb3r/services/crossstudio.py
db0mb3r/services/delimobil.py
db0mb3r/services/dianet.py
db0mb3r/services/dixy.py
db0mb3r/services/dns_shop.py
db0mb3r/services/easypay.py
db0mb3r/services/edostav.py
db0mb3r/services/egroshi.py
db0mb3r/services/eldorado.py
db0mb3r/services/esh_derevenskoe.py
db0mb3r/services/etm.py
db0mb3r/services/finam.py
db0mb3r/services/findclone.py
db0mb3r-3.1.4.17.dist-info/LICENSE
db0mb3r-3.1.4.17.dist-info/METADATA
db0mb3r-3.1.4.17.dist-info/WHEEL
db0mb3r-3.1.4.17.dist-info/entry_points.txt
db0mb3r-3.1.4.17.dist-info/top_level.txt
db0mb3r-3.1.4.17.dist-info/RECORD
