Metadata-Version: 2.1
Name: db0mb3r
Version: 3.1.4.17
Summary: Открытый и бесплатный СМС бомбер
Home-page: https://github.com/dmitrijkotov634/b0mb3r
Author: crinny
Author-email: 
License: Mozilla Public License 2.0
Platform: UNKNOWN
Classifier: Programming Language :: Python
Classifier: Programming Language :: Python :: 3
Classifier: Programming Language :: Python :: 3.7
Classifier: Operating System :: Android
Classifier: Operating System :: Microsoft :: Windows
Classifier: Topic :: Internet
Classifier: License :: OSI Approved :: Mozilla Public License 2.0 (MPL 2.0)
Requires-Python: >=3.7.0
Requires-Dist: wheel
Requires-Dist: fastapi
Requires-Dist: uvicorn
Requires-Dist: aiofiles
Requires-Dist: pydantic
Requires-Dist: jinja2
Requires-Dist: httpx
Requires-Dist: phonenumbers
Requires-Dist: click
Requires-Dist: loguru
Requires-Dist: random-user-agent
Requires-Dist: pip
